pycount_thayehas1/__init__.py
pycount_thayehas1/plotting.py
pycount_thayehas1/pycount_thayehas1.py
pycount_thayehas1-0.1.0.dist-info/LICENSE
pycount_thayehas1-0.1.0.dist-info/WHEEL
pycount_thayehas1-0.1.0.dist-info/METADATA
pycount_thayehas1-0.1.0.dist-info/RECORD
